PardhuEmailSender/__init__.py
PardhuEmailSender/email_sender.py
PardhuEmailSender-0.1.dist-info/LICENSE.txt
PardhuEmailSender-0.1.dist-info/METADATA
PardhuEmailSender-0.1.dist-info/WHEEL
PardhuEmailSender-0.1.dist-info/top_level.txt
PardhuEmailSender-0.1.dist-info/RECORD
