Metadata-Version: 2.1
Name: PardhuEmailSender
Version: 0.1
Summary: This package will allow you to send bulk emails
Home-page: https://github.com/JavaHunt
Download-URL: https://github.com/JavaHunt/PardhuEmailSender/archive/refs/tags/1.0.tar.gz
Author: Mallela Pardha Saradhi
Author-email: pardhu9100@gmail.com
License: MIT
Keywords: Email,Email Bomber,Bulk mails,Gmail,Smtp,Email sender
Classifier: Development Status :: 3 - Alpha
Classifier: Intended Audience :: Developers
Classifier: Topic :: Software Development :: Build Tools
Classifier: License :: OSI Approved :: MIT License
Classifier: Programming Language :: Python :: 3
Classifier: Programming Language :: Python :: 3.4
Classifier: Programming Language :: Python :: 3.5
Classifier: Programming Language :: Python :: 3.6
Classifier: Programming Language :: Python :: 3.7
Classifier: Programming Language :: Python :: 3.8
Classifier: Programming Language :: Python :: 3.9
Classifier: Programming Language :: Python :: 3.10
Classifier: Programming Language :: Python :: 3.11
Classifier: Operating System :: Unix
Classifier: Operating System :: MacOS :: MacOS X
Classifier: Operating System :: Microsoft :: Windows
License-File: LICENSE.txt
Requires-Dist: email
Requires-Dist: smtplib
